[{"id":"3515129875573","cnes":"9875573","noFantasia":"ENEDY BRESCHI SEGATO","noEmpresarial":"ENEDY BRESCHI SEGATO","uf":"SP","noMunicipio":"EMILIANOPOLIS","gestao":"M","natJuridica":"4","atendeSus":"N"},{"id":"3515126781691","cnes":"6781691","noFantasia":"SECRETARIA MUNICIPAL DE SAUDE DE EMILIANOPOLIS","noEmpresarial":"PREFEITURA MUNICIPAL DE EMILIANOPOLIS","uf":"SP","noMunicipio":"EMILIANOPOLIS","gestao":"M","natJuridica":"1","atendeSus":"S"},{"id":"3515122751275","cnes":"2751275","noFantasia":"UNIDADE BASICA DE SAUDE DA SAUDE DA FAMILIA DE EMILIANOPOLIS","noEmpresarial":"PREFEITURA MUNICIPAL DE EMILIANOPOLIS","uf":"SP","noMunicipio":"EMILIANOPOLIS","gestao":"M","natJuridica":"1","atendeSus":"S"}]
