[{"id":"3111152203162","cnes":"2203162","noFantasia":"CENTRO DE SAUDE DE CAMPO AZUL","noEmpresarial":"PREFEITURA MUNICIPAL DE CAMPO AZUL","uf":"MG","noMunicipio":"CAMPO AZUL","gestao":"D","natJuridica":"1","atendeSus":"S"},{"id":"3111150783862","cnes":"0783862","noFantasia":"LABORATORIO ALMEIDA E CUNHA LTDA","noEmpresarial":"LABORATORIO ALMEIDA E CUNHA LTDA","uf":"MG","noMunicipio":"CAMPO AZUL","gestao":"M","natJuridica":"2","atendeSus":"N"},{"id":"3111152203170","cnes":"2203170","noFantasia":"POSTO DE SAUDE DE SAO GREGORIO","noEmpresarial":"PREFEITURA MUNICIPAL DE CAMPO AZUL","uf":"MG","noMunicipio":"CAMPO AZUL","gestao":"M","natJuridica":"1","atendeSus":"S"},{"id":"3111150883220","cnes":"0883220","noFantasia":"POSTO DE SAUDE RIACHO DOS SANTOS","noEmpresarial":"PREFEITURA MUNICIPAL DE CAMPO AZUL","uf":"MG","noMunicipio":"CAMPO AZUL","gestao":"M","natJuridica":"1","atendeSus":"S"},{"id":"3111159531327","cnes":"9531327","noFantasia":"SECRETARIA MUNICIPAL DE SAUDE DE CAMPO AZUL","noEmpresarial":"MUNICIPIO DE CAMPO AZUL","uf":"MG","noMunicipio":"CAMPO AZUL","gestao":"M","natJuridica":"1","atendeSus":"S"},{"id":"3111156391834","cnes":"6391834","noFantasia":"UAPS MATEUS ANTONIO DE MEIRA","noEmpresarial":"PREFEITURA MUNICIPAL DE CAMPO AZUL","uf":"MG","noMunicipio":"CAMPO AZUL","gestao":"M","natJuridica":"1","atendeSus":"S"},{"id":"3111157851243","cnes":"7851243","noFantasia":"VIGILANCIA SANITARIA DE CAMPO AZUL","noEmpresarial":"PREFEITURA MUNICIPAL DE CAMPO AZUL","uf":"MG","noMunicipio":"CAMPO AZUL","gestao":"M","natJuridica":"1","atendeSus":"S"}]
