[{"id":"2111407578601","cnes":"7578601","noFantasia":"ACADEMIA DA SAUDE JOSE CARLOS MOREIRA","noEmpresarial":"PREFEITURA MUNCIPAL DE SAO LUIS GONZAGA DO MARANHAO","uf":"MA","noMunicipio":"SAO LUIS GONZAGA DO MARANHAO","gestao":"M","natJuridica":"1","atendeSus":"S"},{"id":"2111409602550","cnes":"9602550","noFantasia":"CAPS DE SAO LUIS GONZAGA DO MARANHAO","noEmpresarial":"MUNICIPIO DE SAO LUIS GONZAGA DO MARANHAO","uf":"MA","noMunicipio":"SAO LUIS GONZAGA DO MARANHAO","gestao":"M","natJuridica":"1","atendeSus":"S"},{"id":"2111409773916","cnes":"9773916","noFantasia":"CENTRO DE ESPECIALIDADES ODONTOLOGICA CEO TIPO I","noEmpresarial":"MUNICIPIO DE SAO LUIS GONZAGAGA DO MARANHAO","uf":"MA","noMunicipio":"SAO LUIS GONZAGA DO MARANHAO","gestao":"M","natJuridica":"1","atendeSus":"S"},{"id":"2111402310813","cnes":"2310813","noFantasia":"CENTRO DE SAUDE WILSON CURVINA","noEmpresarial":"PREFEITURA MUNICIPAL DE SAO LUIS GONZAGA DO MARANHAO","uf":"MA","noMunicipio":"SAO LUIS GONZAGA DO MARANHAO","gestao":"M","natJuridica":"1","atendeSus":"S"},{"id":"2111406769802","cnes":"6769802","noFantasia":"CONSULTORIO ODONTOLOGICO FUZIODONTO","noEmpresarial":"CONSULTORIO ODONTOLOGICO FUZIODONTO","uf":"MA","noMunicipio":"SAO LUIS GONZAGA DO MARANHAO","gestao":"M","natJuridica":"4","atendeSus":"N"},{"id":"2111402309602","cnes":"2309602","noFantasia":"HOSPITAL MUNICIPAL DR CARLOS MACIEIRA","noEmpresarial":"PREFEITURA MUNICIPAL DE SAO LUIS GONZAGA DO MARANHAO","uf":"MA","noMunicipio":"SAO LUIS GONZAGA DO MARANHAO","gestao":"M","natJuridica":"1","atendeSus":"S"},{"id":"2111400259519","cnes":"0259519","noFantasia":"LABORATORIO DE PROTESE DENTARIA DE SAO LUIS GONZAGA MA","noEmpresarial":"MUNICIPIO DE SAO LUIS GONZAGA DO MARANHAO","uf":"MA","noMunicipio":"SAO LUIS GONZAGA DO MARANHAO","gestao":"M","natJuridica":"1","atendeSus":"S"},{"id":"2111402311186","cnes":"2311186","noFantasia":"POSTO DE SAUDE DE TRES SETUBAL","noEmpresarial":"PREFEITURA MUNICIPAL DE SAO LUIS GONZAGA DO MARANHAO","uf":"MA","noMunicipio":"SAO LUIS GONZAGA DO MARANHAO","gestao":"M","natJuridica":"1","atendeSus":"S"},{"id":"2111406604056","cnes":"6604056","noFantasia":"SEMUS DE SAO LUIS GONZAGA DO MARANHAO","noEmpresarial":"PREFEITURA MUNICIPAL DE SAO LUIS GONZAGA DO MARANHAO","uf":"MA","noMunicipio":"SAO LUIS GONZAGA DO MARANHAO","gestao":"M","natJuridica":"1","atendeSus":"S"},{"id":"2111403390764","cnes":"3390764","noFantasia":"UBPSF DA INVASAO","noEmpresarial":"PREFEITURA MUNICIPAL DE SAO LUIS GONZAGA DO MARANHAO","uf":"MA","noMunicipio":"SAO LUIS GONZAGA DO MARANHAO","gestao":"M","natJuridica":"1","atendeSus":"S"},{"id":"2111403390829","cnes":"3390829","noFantasia":"UBPSF DE MASSARANDUBA DOS GREGORIOS","noEmpresarial":"PREFEITURA MUNICIPAL DE SAO LUIS GONZAGA DO MARANHAO","uf":"MA","noMunicipio":"SAO LUIS GONZAGA DO MARANHAO","gestao":"M","natJuridica":"1","atendeSus":"S"},{"id":"2111403390748","cnes":"3390748","noFantasia":"UBPSF DE SAO DOMINGOS","noEmpresarial":"PREFEITURA MUNICIPAL DE SAO LUIS GONZAGA DO MARANHAO","uf":"MA","noMunicipio":"SAO LUIS GONZAGA DO MARANHAO","gestao":"M","natJuridica":"1","atendeSus":"S"},{"id":"2111403390756","cnes":"3390756","noFantasia":"UBPSF DE TRIZIDELA","noEmpresarial":"PREFEITURA MUNICIPAL DE SAO LUIS GONZAGA DO MARANHAO","uf":"MA","noMunicipio":"SAO LUIS GONZAGA DO MARANHAO","gestao":"M","natJuridica":"1","atendeSus":"S"},{"id":"2111403390772","cnes":"3390772","noFantasia":"UBPSF DO BAIRRO MONTE CRISTO","noEmpresarial":"PREFEITURA MUNICIPAL DE SAO LUIS GONZAGA DO MARANHAO","uf":"MA","noMunicipio":"SAO LUIS GONZAGA DO MARANHAO","gestao":"M","natJuridica":"1","atendeSus":"S"},{"id":"2111403390721","cnes":"3390721","noFantasia":"UBPSF SAO JOAO DO ANTAO","noEmpresarial":"PREFEITURA MUNICIPAL DE SAO LUIS GONZAGA DO MARANHAO","uf":"MA","noMunicipio":"SAO LUIS GONZAGA DO MARANHAO","gestao":"M","natJuridica":"1","atendeSus":"S"},{"id":"2111402453320","cnes":"2453320","noFantasia":"UNIDADE DE SAUDE DA FAMILIA NOVA VIDA","noEmpresarial":"PREFEITURA MUNICIPAL DE SAO LUIS GONZAGA DO MARANHAO","uf":"MA","noMunicipio":"SAO LUIS GONZAGA DO MARANHAO","gestao":"M","natJuridica":"1","atendeSus":"S"},{"id":"2111402452413","cnes":"2452413","noFantasia":"UNIDADE DE SAUDE DA FAMILIA OLHO DAGUA DOS GRILOS","noEmpresarial":"PREFEITURA MUNICIPAL DE SAO LUIS GONZAGA","uf":"MA","noMunicipio":"SAO LUIS GONZAGA DO MARANHAO","gestao":"M","natJuridica":"1","atendeSus":"S"},{"id":"2111409506039","cnes":"9506039","noFantasia":"UNIDADE MOVEL ODONTOLOGICA DE SAO LUIS GONZAGA DO MARANHAO","noEmpresarial":"MUNICIPIO DE SAO LUIS GONZAGA DO MARANHAO","uf":"MA","noMunicipio":"SAO LUIS GONZAGA DO MARANHAO","gestao":"M","natJuridica":"1","atendeSus":"S"},{"id":"2111406604099","cnes":"6604099","noFantasia":"VIGILANCIA SANITARIA E AMBIENTAL","noEmpresarial":"PREFEITURA MUNICIPAL DE SAO LUIS GONZAGA DO MARANHAO","uf":"MA","noMunicipio":"SAO LUIS GONZAGA DO MARANHAO","gestao":"M","natJuridica":"1","atendeSus":"S"}]
