[{"id":"2901107358695","cnes":"7358695","noFantasia":"ACADEMIA DA SAUDE ALYSSON XAVIER DOS SANTOS","noEmpresarial":"MUNICIPIO DE AMELIA RODRIGUES","uf":"BA","noMunicipio":"AMELIA RODRIGUES","gestao":"M","natJuridica":"1","atendeSus":"S"},{"id":"2901106018025","cnes":"6018025","noFantasia":"AMELIA ODONTO","noEmpresarial":"AMELIA ODONTO","uf":"BA","noMunicipio":"AMELIA RODRIGUES","gestao":"M","natJuridica":"2","atendeSus":"N"},{"id":"2901107558171","cnes":"7558171","noFantasia":"CAF CENTRAL DE ABASTECIMENTO FARMACEUTICO","noEmpresarial":"MUNICIPIO DE AMELIA RODRIGUES","uf":"BA","noMunicipio":"AMELIA RODRIGUES","gestao":"M","natJuridica":"1","atendeSus":"S"},{"id":"2901105503299","cnes":"5503299","noFantasia":"CENTRO DE ATENCAO PSICOSOCIAL CAPS I","noEmpresarial":"MUNICIPIO DE AMELIA RODRIGUES","uf":"BA","noMunicipio":"AMELIA RODRIGUES","gestao":"M","natJuridica":"1","atendeSus":"S"},{"id":"2901100226084","cnes":"0226084","noFantasia":"CENTRO DE ATENDIMENTO AO COVID19","noEmpresarial":"CENTRO DE ATENDIMENTO AO COVID19","uf":"BA","noMunicipio":"AMELIA RODRIGUES","gestao":"M","natJuridica":"1","atendeSus":"S"},{"id":"2901105492696","cnes":"5492696","noFantasia":"CENTRO DE REABILITACAO E FISIOTERAPIA DE AMELIA RODRIGUES","noEmpresarial":"MUNICIPIO DE AMELIA RODRIGUES","uf":"BA","noMunicipio":"AMELIA RODRIGUES","gestao":"D","natJuridica":"1","atendeSus":"S"},{"id":"2901109178813","cnes":"9178813","noFantasia":"CENTRO MEDICO ALIANCA","noEmpresarial":"A M DE JESUS CLINICA MEDICA ME","uf":"BA","noMunicipio":"AMELIA RODRIGUES","gestao":"E","natJuridica":"2","atendeSus":"N"},{"id":"2901102602326","cnes":"2602326","noFantasia":"CLIOF CLINICA OFTALMOLOGICA","noEmpresarial":"OSVALDETE DURVALINA SANTOS","uf":"BA","noMunicipio":"AMELIA RODRIGUES","gestao":"E","natJuridica":"2","atendeSus":"S"},{"id":"2901107128959","cnes":"7128959","noFantasia":"ESPACO FISIO SAUDE","noEmpresarial":"E MONIZ DE JESUS","uf":"BA","noMunicipio":"AMELIA RODRIGUES","gestao":"E","natJuridica":"2","atendeSus":"N"},{"id":"2901102799723","cnes":"2799723","noFantasia":"GRIMLAB","noEmpresarial":"GRIMALDO MATOS CABRAL","uf":"BA","noMunicipio":"AMELIA RODRIGUES","gestao":"E","natJuridica":"2","atendeSus":"S"},{"id":"2901102799103","cnes":"2799103","noFantasia":"HPP DR PEDRO AMERICO DE BRITO","noEmpresarial":"MUNICIPIO DE AMELIA RODRIGUES","uf":"BA","noMunicipio":"AMELIA RODRIGUES","gestao":"D","natJuridica":"1","atendeSus":"S"},{"id":"2901106015743","cnes":"6015743","noFantasia":"ODONTO CLIN","noEmpresarial":"RAQUELLY CRISTINA ROCHA DOS ANJOS E CIA","uf":"BA","noMunicipio":"AMELIA RODRIGUES","gestao":"M","natJuridica":"4","atendeSus":"N"},{"id":"2901109747184","cnes":"9747184","noFantasia":"ODONTO MAIS","noEmpresarial":"ADRIANA DE ARAUJO LEE","uf":"BA","noMunicipio":"AMELIA RODRIGUES","gestao":"M","natJuridica":"2","atendeSus":"N"},{"id":"2901106388949","cnes":"6388949","noFantasia":"SECRETARIA MUNICIPAL DE SAUDE DE AMELIA RODRIGUES","noEmpresarial":"MUNICIPIO DE AMELIA RODRIGUES","uf":"BA","noMunicipio":"AMELIA RODRIGUES","gestao":"D","natJuridica":"1","atendeSus":"S"},{"id":"2901100092495","cnes":"0092495","noFantasia":"UNIDADE REGIONAL DE SUPORTE BASICO DE URG E EME","noEmpresarial":"MUNICIPIO DE AMELIA RODRIGUES","uf":"BA","noMunicipio":"AMELIA RODRIGUES","gestao":"M","natJuridica":"1","atendeSus":"S"},{"id":"2901103027031","cnes":"3027031","noFantasia":"USF CELINA BRITTO","noEmpresarial":"MUNICIPIO DE AMELIA RODRIGUES","uf":"BA","noMunicipio":"AMELIA RODRIGUES","gestao":"M","natJuridica":"1","atendeSus":"S"},{"id":"2901109416277","cnes":"9416277","noFantasia":"USF CENTO E QUINZE","noEmpresarial":"MUNICIPIO DE AMELIA RODRIGUES","uf":"BA","noMunicipio":"AMELIA RODRIGUES","gestao":"M","natJuridica":"1","atendeSus":"S"},{"id":"2901102771543","cnes":"2771543","noFantasia":"USF DE SAO BENTO","noEmpresarial":"MUNICIPIO DE AMELIA RODRIGUES","uf":"BA","noMunicipio":"AMELIA RODRIGUES","gestao":"M","natJuridica":"1","atendeSus":"S"},{"id":"2901103507939","cnes":"3507939","noFantasia":"USF DO CAMPO ALEGRE","noEmpresarial":"MUNICIPIO DE AMELIA RODRIGUES","uf":"BA","noMunicipio":"AMELIA RODRIGUES","gestao":"M","natJuridica":"1","atendeSus":"S"},{"id":"2901109416250","cnes":"9416250","noFantasia":"USF DOS CAMPOS","noEmpresarial":"MUNICIPIO DE AMELIA RODRIGUES","uf":"BA","noMunicipio":"AMELIA RODRIGUES","gestao":"M","natJuridica":"1","atendeSus":"S"},{"id":"2901103161757","cnes":"3161757","noFantasia":"USF ELIANA CARDOSO","noEmpresarial":"MUNICIPIO DE AMELIA RODRIGUES","uf":"BA","noMunicipio":"AMELIA RODRIGUES","gestao":"M","natJuridica":"1","atendeSus":"S"},{"id":"2901102771748","cnes":"2771748","noFantasia":"USF ITAPICURU","noEmpresarial":"MUNICIPIO DE AMELIA RODRIGUES","uf":"BA","noMunicipio":"AMELIA RODRIGUES","gestao":"D","natJuridica":"1","atendeSus":"S"},{"id":"2901102772388","cnes":"2772388","noFantasia":"USF ITAPICURU B","noEmpresarial":"MUNICIPIO DE AMELIA RODRIGUES","uf":"BA","noMunicipio":"AMELIA RODRIGUES","gestao":"M","natJuridica":"1","atendeSus":"S"},{"id":"2901106369456","cnes":"6369456","noFantasia":"USF MARIA LIBANIA DE JESUS","noEmpresarial":"MUNICIPIO DE AMELIA RODRIGUES","uf":"BA","noMunicipio":"AMELIA RODRIGUES","gestao":"M","natJuridica":"1","atendeSus":"S"},{"id":"2901109416293","cnes":"9416293","noFantasia":"USF SAO BENTO II","noEmpresarial":"MUNICIPIO DE AMELIA RODRIGUES","uf":"BA","noMunicipio":"AMELIA RODRIGUES","gestao":"M","natJuridica":"1","atendeSus":"S"},{"id":"2901109725687","cnes":"9725687","noFantasia":"VITAILABORATORIO E IMAGEM","noEmpresarial":"KNC MEDICINA DIAGNOSTICA LTDA","uf":"BA","noMunicipio":"AMELIA RODRIGUES","gestao":"M","natJuridica":"2","atendeSus":"N"}]
